{
  "categories": {
    "0_mooc": {
      "category": "MOOC Introducción",
      "description": "Preguntas relacionadas con el curso de EdX \"Android: Introducción a la programación\"",
      "theme": "blue",
      "img": "http://mmoviles.upv.es/trivial/img/edx.png",
      "video": "",
      "moreinfo": "https://www.edx.org/course/android-introduccion-la-programacion-upvalenciax-aip201x-1",
      "subcategories": {
        "0_java": {
          "category": "Java y POO",
          "description": "Comprueba tus conocimientos sobre Java y Programación Orientada a Objetos.",
          "theme": "blue",
          "img": "http://mmoviles.upv.es/trivial/img/java.png",
          "video": "https://youtu.be/nGVmgHUo7sA",
          "moreinfo": "http://www.androidcurso.com/index.php/21",
          "subcategories": {
            "0_java_conocimientos": {
              "category": "Conocimientos previos en C, Java y POO",
              "description": "Comprueba tus conocimientos sobre Java y Programación Orientada a Objetos.",
              "quiz": "http://mmoviles.upv.es/test_fundamentos/0_0%20Conocimientos%20previos%20en%20C%20Java%20y%20POO.txt"
            },
            "1_java_caracteriasticas": {
              "video": "https://youtu.be/Mmmrp8PRLOo",
              "moreinfo": "http://www.dcomg.upv.es/~jtomas/android/unidad_0/Caracter%C3%ADsticas%20de%20Java.pdf",
              "quiz": "http://mmoviles.upv.es/test_fundamentos/0_1%20caracteristicas%20de%20Java.txt"
            }
            ...
          }
        }
       ...
      }
    },
    "1_fundamentos": {
      "category": "Android Fundamentos",
      "description": "Preguntas relacionadas con el curso \"Android: Fundamentos\" o El Gran Libro de Amdroid",
      "theme": "green",
      "img": "http://mmoviles.upv.es/trivial/img/android.png",
      "video": "",
      "moreinfo": "http://www.androidcurso.com/index.php/modulo-avanzado/programa-fundamentos",
      "subcategories": {
        "1_intro": {
          "category": "La plataforma Android",
          "description": "Introducción a la plataforma android y al entorno de desarrollo Android Studio.",
          "theme": "green",
          "img": "http://mmoviles.upv.es/trivial/img/Android_Studio.png",
          "video": "",
          "moreinfo": "http://www.androidcurso.com/index.php/96",
          "quizzes": [
            "http://mmoviles.upv.es/test_fundamentos/1_1%20Que%20hace%20de_%20y%20Origenes.txt",
            "http://mmoviles.upv.es/test_fundamentos/1_8 Elementos de un proyecto.txt"
          ]
        }
      }
    }
    ...
  }
}